{"assets/BienHecho.png":["assets/BienHecho.png"],"assets/Fondo.jpg":["assets/Fondo.jpg"],"assets/FondoMonedas2.jpg":["assets/FondoMonedas2.jpg"],"assets/FondoTrofeo.jpg":["assets/FondoTrofeo.jpg"],"assets/Trofeo.png":["assets/Trofeo.png"],"assets/bolsaDinero.png":["assets/bolsaDinero.png"],"assets/btnStart.png":["assets/btnStart.png"],"assets/cartel.png":["assets/cartel.png"],"assets/fondoFinal.png":["assets/fondoFinal.png"],"assets/fonts/pixelart.ttf":["assets/fonts/pixelart.ttf"],"assets/guide.png":["assets/guide.png"],"assets/senal.png":["assets/senal.png"],"assets/silueta.png":["assets/silueta.png"],"packages/cupertino_icons/assets/CupertinoIcons.ttf":["packages/cupertino_icons/assets/CupertinoIcons.ttf"]}